metget/__init__.py
metget/metget_adeck.py
metget/metget_build.py
metget/metget_client.py
metget/metget_credits.py
metget/metget_data.py
metget/metget_environment.py
metget/metget_status.py
metget/metget_track.py
metget/spinnerlogger.py
metget-0.11.0.dist-info/licenses/LICENSE.md
metget-0.11.0.dist-info/METADATA
metget-0.11.0.dist-info/WHEEL
metget-0.11.0.dist-info/entry_points.txt
metget-0.11.0.dist-info/top_level.txt
metget-0.11.0.dist-info/RECORD
