Metadata-Version: 2.4
Name: metget
Version: 0.11.0
Summary: A client package for interaction with a MetGet server instance
Author-email: Zach Cobell <zcobell@thewaterinstitute.org>
License: MIT
Project-URL: Homepage, https://github.com/waterinstitute/metget
Project-URL: Bug Reports, https://github.com/waterinstitute/metget/issues
Project-URL: Source, https://github.com/waterinstitute/metget
Keywords: forecast,meteorology,stormsurge
Classifier: Programming Language :: Python :: 3
Classifier: Development Status :: 4 - Beta
Classifier: License :: OSI Approved :: MIT License
Classifier: Environment :: Console
Classifier: Intended Audience :: Science/Research
Classifier: Topic :: Scientific/Engineering :: Atmospheric Science
Classifier: Topic :: Scientific/Engineering :: Hydrology
Classifier: Operating System :: OS Independent
Requires-Python: >=3.8
License-File: LICENSE.md
Requires-Dist: requests
Requires-Dist: yaspin
Requires-Dist: prettytable
Dynamic: license-file
